setup.cfg
setup.py
pushalot/__init__.py
pushalot/apis.py
pushalot/exc.py
pushalot/factory.py
pushalot/transport.py
pushalot.egg-info/PKG-INFO
pushalot.egg-info/SOURCES.txt
pushalot.egg-info/dependency_links.txt
pushalot.egg-info/not-zip-safe
pushalot.egg-info/requires.txt
pushalot.egg-info/top_level.txt
tests/__init__.py
tests/test_apis.py
tests/test_factory.py
tests/test_transport.py