Metadata-Version: 1.1
Name: pushalot
Version: 0.1
Summary: Wrapper for pushalot.com service
Home-page: https://github.com/bosha/pypushalot
Author: Alex Bo
Author-email: public@the-bosha.ru
License: MIT
Keywords: pushalot,push,api,windowsphone,wp
Platform: UNKNOWN
Classifier: License :: OSI Approved :: MIT License
Classifier: Programming Language :: Python :: 2.7
Classifier: Programming Language :: Python :: 3.4
